{"_type":"export","__export_format":4,"__export_date":"2020-03-29T03:52:09.784Z","__export_source":"insomnia.desktop.app:v7.1.1","resources":[{"_id":"req_248e998b580c43be95cf4978a081ffff","authentication":{},"body":{"mimeType":"application/json","text":"{\n\t\"email\": \"lucas_ss.arts@live.com\",\n\t\"password\": \"123456\"\n}"},"created":1585437444932,"description":"","headers":[{"id":"pair_b2adfd1432c347918676e287fcf937a1","name":"Content-Type","value":"application/json"}],"isPrivate":false,"metaSortKey":-1585437444932,"method":"POST","modified":1585437528358,"name":"Create User","parameters":[],"parentId":"fld_01307a07f8bf4b079df2329348770c47","settingDisableRenderRequestBody":false,"settingEncodeUrl":true,"settingFollowRedirects":"global","settingRebuildPath":true,"settingSendCookies":true,"settingStoreCookies":true,"url":"{{ base_url  }}/session-user","_type":"request"},{"_id":"fld_01307a07f8bf4b079df2329348770c47","created":1585090727228,"description":"","environment":{},"environmentPropertyOrder":null,"metaSortKey":-1585090727228,"modified":1585090727228,"name":"Login","parentId":"fld_605af32375e9446ab8008079f5f48288","_type":"request_group"},{"_id":"fld_605af32375e9446ab8008079f5f48288","created":1585066384720,"description":"","environment":{"base_url":"http://localhost:3333","ong_id":"82dff13c","token":"eyJhbGciOiJIUzI1NiIsInR5cCI6IkpXVCJ9.eyJpZCI6IjQwM2JlYTk0IiwibmFtZSI6IkFzc29jaWHDp8OjbyBkZSBDdWlkYWRvIGFvcyBBbmltYWlzIGRlIFJ1YSIsImlhdCI6MTU4NTQzNzUzNSwiZXhwIjoxNTg2MDQyMzM1fQ.9p072Zxef18kHC81neuPLPh8g74Qi5rnXlZ8QBsl3sg"},"environmentPropertyOrder":{"&":["base_url","ong_id","token"]},"metaSortKey":-1585066384721,"modified":1585437569772,"name":"omnistack11","parentId":"wrk_6dd04d20017e42cd9b3a2a2c8d9db4a7","_type":"request_group"},{"_id":"wrk_6dd04d20017e42cd9b3a2a2c8d9db4a7","created":1582653061642,"description":"","modified":1582653061642,"name":"Insomnia","parentId":null,"_type":"workspace"},{"_id":"req_2132883b0b984a03a45ebb8f904dadde","authentication":{},"body":{"mimeType":"application/json","text":"{\n\t\"id\": \"403bea94\",\n\t\"password\": \"123456\"\n}"},"created":1585090731844,"description":"","headers":[{"id":"pair_cc002f3e3d9741808d75977bf9e38e69","name":"Content-Type","value":"application/json"}],"isPrivate":false,"metaSortKey":-1585090731844,"method":"POST","modified":1585437531269,"name":"Create ONG","parameters":[],"parentId":"fld_01307a07f8bf4b079df2329348770c47","settingDisableRenderRequestBody":false,"settingEncodeUrl":true,"settingFollowRedirects":"global","settingRebuildPath":true,"settingSendCookies":true,"settingStoreCookies":true,"url":"{{ base_url  }}/session-ong","_type":"request"},{"_id":"req_d8d4f50d6f4749e4b6e9f51e45be0350","authentication":{"token":"{{ token  }}","type":"bearer"},"body":{},"created":1585066581053,"description":"","headers":[{"description":"","id":"pair_0a368ddb735e4c2ea8c0ad3f7a04fdc5","name":"","value":""}],"isPrivate":false,"metaSortKey":-1585066581053,"method":"GET","modified":1585453206673,"name":"List","parameters":[],"parentId":"fld_f6f9e7d81cb04349b379556a15d578a9","settingDisableRenderRequestBody":false,"settingEncodeUrl":true,"settingFollowRedirects":"global","settingRebuildPath":true,"settingSendCookies":true,"settingStoreCookies":true,"url":"{{ base_url  }}/ong","_type":"request"},{"_id":"fld_f6f9e7d81cb04349b379556a15d578a9","created":1585066396217,"description":"","environment":{},"environmentPropertyOrder":null,"metaSortKey":-1585066396217,"modified":1585066396217,"name":"Ongs","parentId":"fld_605af32375e9446ab8008079f5f48288","_type":"request_group"},{"_id":"req_a3dc2d72363f413da0b52034e80f749b","authentication":{},"body":{"mimeType":"application/json","text":"{\n\t\"name\": \"APAD\",\n\t\"email\": \"cristianocardoso45\",\n\t\"password\": \"123456\",\n\t\"whatsapp\": \"11985412365\",\n\t\"city\": \"Praia Grande\",\n\t\"state\": \"SP\"\n}"},"created":1585066389088,"description":"","headers":[{"id":"pair_d4f66e4302654167bcd69b7e68486224","name":"Content-Type","value":"application/json"}],"isPrivate":false,"metaSortKey":-1585066392652.5,"method":"POST","modified":1585427088558,"name":"Create","parameters":[],"parentId":"fld_f6f9e7d81cb04349b379556a15d578a9","settingDisableRenderRequestBody":false,"settingEncodeUrl":true,"settingFollowRedirects":"global","settingRebuildPath":true,"settingSendCookies":true,"settingStoreCookies":true,"url":"{{ base_url  }}/ong","_type":"request"},{"_id":"req_86327c84956b4bbabe619267d7f552dc","authentication":{"token":"{{ token  }}","type":"bearer"},"body":{},"created":1585438428199,"description":"","headers":[{"description":"","id":"pair_0a368ddb735e4c2ea8c0ad3f7a04fdc5","name":"","value":""}],"isPrivate":false,"metaSortKey":-1585066581053,"method":"GET","modified":1585438464238,"name":"List","parameters":[],"parentId":"fld_c33d179e04d645e2b553bf44d822ae90","settingDisableRenderRequestBody":false,"settingEncodeUrl":true,"settingFollowRedirects":"global","settingRebuildPath":true,"settingSendCookies":true,"settingStoreCookies":true,"url":"{{ base_url  }}/user","_type":"request"},{"_id":"fld_c33d179e04d645e2b553bf44d822ae90","created":1585438428165,"description":"","environment":{},"environmentPropertyOrder":null,"metaSortKey":-1585066394409.75,"modified":1585438428165,"name":"User","parentId":"fld_605af32375e9446ab8008079f5f48288","_type":"request_group"},{"_id":"req_a93e12986fb44d3dbd10e8cccf0d248a","authentication":{},"body":{"mimeType":"application/json","text":"{\n\t\"name\": \"APAD\",\n\t\"email\": \"cristianocardoso45@h.com\",\n\t\"password\": \"123456\",\n\t\"whatsapp\": \"11985412365\",\n\t\"city\": \"Praia Grande\",\n\t\"state\": \"SP\"\n}"},"created":1585438428187,"description":"","headers":[{"id":"pair_d4f66e4302654167bcd69b7e68486224","name":"Content-Type","value":"application/json"}],"isPrivate":false,"metaSortKey":-1585066392652.5,"method":"POST","modified":1585452855298,"name":"Create","parameters":[],"parentId":"fld_c33d179e04d645e2b553bf44d822ae90","settingDisableRenderRequestBody":false,"settingEncodeUrl":true,"settingFollowRedirects":"global","settingRebuildPath":true,"settingSendCookies":true,"settingStoreCookies":true,"url":"{{ base_url  }}/ong","_type":"request"},{"_id":"req_3ee885311ee04eb6a4666b493d511c61","authentication":{"token":"{{ token  }}","type":"bearer"},"body":{},"created":1585090101924,"description":"","headers":[],"isPrivate":false,"metaSortKey":-1585090101924,"method":"GET","modified":1585438078947,"name":"Show","parameters":[],"parentId":"fld_409d0846ed774225bf269e26302f215a","settingDisableRenderRequestBody":false,"settingEncodeUrl":true,"settingFollowRedirects":"global","settingRebuildPath":true,"settingSendCookies":true,"settingStoreCookies":true,"url":"{{ base_url  }}/incident/2","_type":"request"},{"_id":"fld_409d0846ed774225bf269e26302f215a","created":1585089211824,"description":"","environment":{},"environmentPropertyOrder":null,"metaSortKey":-1585066390469,"modified":1585089211824,"name":"Incidents","parentId":"fld_605af32375e9446ab8008079f5f48288","_type":"request_group"},{"_id":"req_c68331a77ad9455684a81c0d1b20cba4","authentication":{"token":"{{ token  }}","type":"bearer"},"body":{},"created":1585089747108,"description":"","headers":[{"description":"","id":"pair_a18b41d6b7cc4dc7a24c8ce8557612e1","name":"ong_id","value":"{{ ong_id  }}"}],"isPrivate":false,"metaSortKey":-1585089747108,"method":"DELETE","modified":1585438178504,"name":"Delete","parameters":[],"parentId":"fld_409d0846ed774225bf269e26302f215a","settingDisableRenderRequestBody":false,"settingEncodeUrl":true,"settingFollowRedirects":"global","settingRebuildPath":true,"settingSendCookies":true,"settingStoreCookies":true,"url":"{{ base_url  }}/incident/2","_type":"request"},{"_id":"req_ea888a84545742ddbbb515153c7ed13f","authentication":{"token":"{{ token  }}","type":"bearer"},"body":{},"created":1585089211894,"description":"","headers":[],"isPrivate":false,"metaSortKey":-1585066581053,"method":"GET","modified":1585438089325,"name":"List","parameters":[],"parentId":"fld_409d0846ed774225bf269e26302f215a","settingDisableRenderRequestBody":false,"settingEncodeUrl":true,"settingFollowRedirects":"global","settingRebuildPath":true,"settingSendCookies":true,"settingStoreCookies":true,"url":"{{ base_url  }}/incident?page=1","_type":"request"},{"_id":"req_4e10d12d84ca4b7da95a8ee43ea9a74b","authentication":{"token":"{{ token  }}","type":"bearer"},"body":{"mimeType":"application/json","text":"{\n\t\"title\": \"Caso 13\",\n\t\"description\": \"Detalhes do caso\",\n\t\"value\": 120\n}"},"created":1585089211873,"description":"","headers":[{"id":"pair_d4f66e4302654167bcd69b7e68486224","name":"Content-Type","value":"application/json"},{"description":"","id":"pair_492307395243463299d8ece0d7cd46a4","name":"authorization","value":"{{ ong_id  }}"}],"isPrivate":false,"metaSortKey":-1585066392652.5,"method":"POST","modified":1585438359096,"name":"Create","parameters":[],"parentId":"fld_409d0846ed774225bf269e26302f215a","settingDisableRenderRequestBody":false,"settingEncodeUrl":true,"settingFollowRedirects":"global","settingRebuildPath":true,"settingSendCookies":true,"settingStoreCookies":true,"url":"{{ base_url  }}/incident","_type":"request"},{"_id":"req_57571515a9d44705b3ef7eb305352920","authentication":{"token":"{{ token  }}","type":"bearer"},"body":{},"created":1585090339520,"description":"","headers":[{"description":"","disabled":false,"id":"pair_dd8d1144b4fd49798df0517ada3224f7","name":"ong_id","value":"{{ ong_id  }}"}],"isPrivate":false,"metaSortKey":-1585090339520,"method":"GET","modified":1585438402500,"name":"List","parameters":[],"parentId":"fld_c3d3150127e54af8be47c0577e0b5f51","settingDisableRenderRequestBody":false,"settingEncodeUrl":true,"settingFollowRedirects":"global","settingRebuildPath":true,"settingSendCookies":true,"settingStoreCookies":true,"url":"{{ base_url  }}/profile","_type":"request"},{"_id":"fld_c3d3150127e54af8be47c0577e0b5f51","created":1585090334921,"description":"","environment":{},"environmentPropertyOrder":null,"metaSortKey":-1585066392602.5,"modified":1585090352736,"name":"Profile","parentId":"fld_409d0846ed774225bf269e26302f215a","_type":"request_group"},{"_id":"env_5ccdc35cabbb3ab9b714a959d305c317828ce64a","color":null,"created":1582653061716,"data":{},"dataPropertyOrder":null,"isPrivate":false,"metaSortKey":1582653061716,"modified":1582653061716,"name":"Base Environment","parentId":"wrk_6dd04d20017e42cd9b3a2a2c8d9db4a7","_type":"environment"},{"_id":"jar_5ccdc35cabbb3ab9b714a959d305c317828ce64a","cookies":[],"created":1582653061719,"modified":1582653061719,"name":"Default Jar","parentId":"wrk_6dd04d20017e42cd9b3a2a2c8d9db4a7","_type":"cookie_jar"}]}